_XLAC.cpython-310-x86_64-linux-gnu.so
torch_xla/__init__.py
torch_xla/_patched_functions.py
torch_xla/py.typed
torch_xla/runtime.py
torch_xla/stablehlo.py
torch_xla/tf_saved_model_integration.py
torch_xla/torch_xla.py
torch_xla/version.py
torch_xla/_dynamo/__init__.py
torch_xla/_dynamo/config.py
torch_xla/_dynamo/dynamo_backend2.py
torch_xla/_dynamo/dynamo_bridge.py
torch_xla/_internal/__init__.py
torch_xla/_internal/c10d_registration.py
torch_xla/_internal/custom_kernel.py
torch_xla/_internal/decomp_registration.py
torch_xla/_internal/jax_workarounds.py
torch_xla/_internal/neuron.py
torch_xla/_internal/neuron_utils.py
torch_xla/_internal/pjrt.py
torch_xla/_internal/rendezvous.py
torch_xla/_internal/tpu.py
torch_xla/_internal/utils.py
torch_xla/_internal/xpu.py
torch_xla/amp/__init__.py
torch_xla/amp/autocast_mode.py
torch_xla/amp/syncfree/__init__.py
torch_xla/amp/syncfree/_functional.py
torch_xla/amp/syncfree/adam.py
torch_xla/amp/syncfree/adamw.py
torch_xla/amp/syncfree/sgd.py
torch_xla/backends/__init__.py
torch_xla/core/__init__.py
torch_xla/core/dynamo_bridge.py
torch_xla/core/functions.py
torch_xla/core/xla_builder.py
torch_xla/core/xla_env_vars.py
torch_xla/core/xla_model.py
torch_xla/core/xla_op_registry.py
torch_xla/debug/__init__.py
torch_xla/debug/frame_parser_util.py
torch_xla/debug/graph_saver.py
torch_xla/debug/metrics.py
torch_xla/debug/metrics_compare_utils.py
torch_xla/debug/metrics_saver.py
torch_xla/debug/model_comparator.py
torch_xla/debug/profiler.py
torch_xla/distributed/__init__.py
torch_xla/distributed/data_parallel.py
torch_xla/distributed/parallel_loader.py
torch_xla/distributed/xla_backend.py
torch_xla/distributed/xla_multiprocessing.py
torch_xla/distributed/zero_redundancy_optimizer.py
torch_xla/distributed/fsdp/__init__.py
torch_xla/distributed/fsdp/_init_utils.py
torch_xla/distributed/fsdp/consolidate_sharded_ckpts.py
torch_xla/distributed/fsdp/state_dict_utils.py
torch_xla/distributed/fsdp/utils.py
torch_xla/distributed/fsdp/wrap.py
torch_xla-2.9.0.dist-info/licenses/LICENSE
torch_xla-2.9.0.dist-info/METADATA
torch_xla-2.9.0.dist-info/WHEEL
torch_xla-2.9.0.dist-info/entry_points.txt
torch_xla-2.9.0.dist-info/top_level.txt
torch_xla-2.9.0.dist-info/RECORD
