Metadata-Version: 2.4
Name: torch-xla
Version: 2.9.0
Summary: XLA bridge for PyTorch
Home-page: https://github.com/pytorch/xla
Author: PyTorch/XLA Dev Team
Author-email: PyTorch/XLA Dev Team <pytorch-xla@googlegroups.com>
License: Copyright (c) 2018 Google Inc.
Project-URL: Homepage, https://github.com/pytorch/xla
Project-URL: Repository, https://github.com/pytorch/xla
Project-URL: Bug Tracker, https://github.com/pytorch/xla/issues
Keywords: pytorch,xla,tpu,deep learning,compiler
Classifier: Development Status :: 5 - Production/Stable
Classifier: Intended Audience :: Developers
Classifier: Intended Audience :: Science/Research
Classifier: License :: OSI Approved :: BSD License
Classifier: Programming Language :: Python :: 3
Classifier: Programming Language :: Python :: 3.10
Classifier: Programming Language :: Python :: 3.11
Classifier: Programming Language :: Python :: 3.12
Classifier: Topic :: Scientific/Engineering :: Artificial Intelligence
Classifier: Topic :: Software Development :: Libraries :: Python Modules
Requires-Python: >=3.10.0
License-File: LICENSE
Requires-Dist: absl-py>=1.0.0
Requires-Dist: numpy
Requires-Dist: pyyaml
Requires-Dist: requests
Requires-Dist: importlib_metadata>=4.6; python_version < "3.10"
Provides-Extra: tpu
Requires-Dist: libtpu==0.0.21; extra == "tpu"
Requires-Dist: tpu-info; extra == "tpu"
Provides-Extra: pallas
Requires-Dist: jaxlib==0.7.1; extra == "pallas"
Requires-Dist: jax==0.7.1; extra == "pallas"
Dynamic: author
Dynamic: home-page
Dynamic: license-file
Dynamic: provides-extra
Dynamic: requires-dist
Dynamic: requires-python
